MANIFEST.in
README.md
setup.py
applications/__init__.py
applications/admin.py
applications/apps.py
applications/models.py
applications/tests.py
applications/views.py
applications/migrations/0001_initial.py
applications/migrations/0002_initial.py
applications/migrations/__init__.py
design/__init__.py
design/admin.py
design/apps.py
design/models.py
design/script_file_header.py
design/tests.py
design/types.py
design/utils.py
design/views.py
design/migrations/0001_initial.py
design/migrations/__init__.py
django-erp-os-framework/__init__.py
django-erp-os-framework/asgi.py
django-erp-os-framework/celery.py
django-erp-os-framework/settings.py
django-erp-os-framework/urls.py
django-erp-os-framework/views.py
django-erp-os-framework/wsgi.py
django-erp-os-framework/__pycache__/__init__.cpython-311.pyc
django-erp-os-framework/__pycache__/__init__.cpython-312.pyc
django-erp-os-framework/__pycache__/asgi.cpython-311.pyc
django-erp-os-framework/__pycache__/asgi.cpython-312.pyc
django-erp-os-framework/__pycache__/celery.cpython-311.pyc
django-erp-os-framework/__pycache__/settings.cpython-311.pyc
django-erp-os-framework/__pycache__/settings.cpython-312.pyc
django-erp-os-framework/__pycache__/urls.cpython-311.pyc
django-erp-os-framework/__pycache__/urls.cpython-312.pyc
django-erp-os-framework/__pycache__/views.cpython-311.pyc
django-erp-os-framework/__pycache__/views.cpython-312.pyc
django-erp-os-framework/__pycache__/wsgi.cpython-311.pyc
django-erp-os-framework/__pycache__/wsgi.cpython-312.pyc
django_erp_os_framework.egg-info/PKG-INFO
django_erp_os_framework.egg-info/SOURCES.txt
django_erp_os_framework.egg-info/dependency_links.txt
django_erp_os_framework.egg-info/entry_points.txt
django_erp_os_framework.egg-info/requires.txt
django_erp_os_framework.egg-info/top_level.txt
kernel/__init__.py
kernel/admin.py
kernel/app_types.py
kernel/apps.py
kernel/consumers.py
kernel/models.py
kernel/routing.py
kernel/scheduler.py
kernel/signals.py
kernel/sys_lib.py
kernel/tasks.py
kernel/tests.py
kernel/types.py
kernel/urls.py
kernel/utils.py
kernel/views.py
kernel/migrations/0001_initial.py
kernel/migrations/__init__.py