Metadata-Version: 2.1
Name: django-erp-os-framework
Version: 1.0.7
Requires-Dist: django>=4.2
